{
  "__inputs": [
    {
      "name": "DS_PROMETHEUS",
      "label": "Prometheus",
      "description": "",
      "type": "datasource",
      "pluginId": "prometheus",
      "pluginName": "Prometheus"
    }
  ],
  "__requires": [
    {
      "type": "grafana",
      "id": "grafana",
      "name": "Grafana",
      "version": "4.6.3"
    },
    {
      "type": "panel",
      "id": "graph",
      "name": "Graph",
      "version": ""
    },
    {
      "type": "datasource",
      "id": "prometheus",
      "name": "Prometheus",
      "version": "1.0.0"
    }
  ],
  "annotations": {
    "list": [
      {
        "builtIn": 1,
        "datasource": "-- Grafana --",
        "enable": true,
        "hide": true,
        "iconColor": "rgba(0, 211, 255, 1)",
        "name": "Annotations & Alerts",
        "type": "dashboard"
      }
    ]
  },
  "editable": true,
  "gnetId": null,
  "graphTooltip": 0,
  "hideControls": false,
  "id": null,
  "links": [],
  "refresh": false,
  "rows": [
    {
      "collapse": false,
      "height": 250,
      "panels": [
        {
          "alert": {
            "conditions": [
              {
                "evaluator": {
                  "params": [
                    1000
                  ],
                  "type": "gt"
                },
                "operator": {
                  "type": "and"
                },
                "query": {
                  "datasourceId": 1,
                  "model": {
                    "expr": "rate(gm_celery_task_count[30s])",
                    "intervalFactor": 2,
                    "legendFormat": "{{service}}:{{worker_name}}:{{event_type}}",
                    "metric": "gm_celery_task_count",
                    "refId": "A",
                    "step": 10
                  },
                  "params": [
                    "A",
                    "5m",
                    "now"
                  ]
                },
                "reducer": {
                  "params": [],
                  "type": "avg"
                },
                "type": "query"
              }
            ],
            "executionErrorState": "alerting",
            "frequency": "15m",
            "handler": 1,
            "message": "",
            "name": "GM-celery task rate alert",
            "noDataState": "no_data",
            "notifications": [
              {
                "id": 3
              },
              {
                "id": 2
              }
            ]
          },
          "aliasColors": {},
          "bars": false,
          "dashLength": 10,
          "dashes": false,
          "datasource": "${DS_PROMETHEUS}",
          "editable": true,
          "error": false,
          "fill": 0,
          "id": 1,
          "legend": {
            "avg": false,
            "current": false,
            "max": false,
            "min": false,
            "show": true,
            "total": false,
            "values": false
          },
          "lines": true,
          "linewidth": 1,
          "links": [],
          "nullPointMode": "connected",
          "percentage": false,
          "pointradius": 5,
          "points": false,
          "renderer": "flot",
          "seriesOverrides": [],
          "spaceLength": 10,
          "span": 12,
          "stack": false,
          "steppedLine": false,
          "targets": [
            {
              "expr": "rate(gm_celery_task_count[30s])",
              "format": "time_series",
              "intervalFactor": 2,
              "legendFormat": "{{service}}:{{worker_name}}:{{event_type}}",
              "metric": "gm_celery_task_count",
              "refId": "A",
              "step": 10
            }
          ],
          "thresholds": [
            {
              "colorMode": "critical",
              "fill": true,
              "line": true,
              "op": "gt",
              "value": 1000
            }
          ],
          "timeFrom": null,
          "timeShift": null,
          "title": "GM-celery task rate",
          "tooltip": {
            "msResolution": false,
            "shared": true,
            "sort": 0,
            "value_type": "individual"
          },
          "type": "graph",
          "xaxis": {
            "buckets": null,
            "mode": "time",
            "name": null,
            "show": true,
            "values": []
          },
          "yaxes": [
            {
              "format": "short",
              "label": null,
              "logBase": 1,
              "max": null,
              "min": null,
              "show": true
            },
            {
              "format": "short",
              "label": null,
              "logBase": 1,
              "max": null,
              "min": null,
              "show": true
            }
          ]
        }
      ],
      "repeat": null,
      "repeatIteration": null,
      "repeatRowId": null,
      "showTitle": false,
      "title": "Dashboard Row",
      "titleSize": "h6"
    },
    {
      "collapse": false,
      "height": 250,
      "panels": [
        {
          "alert": {
            "conditions": [
              {
                "evaluator": {
                  "params": [
                    10000
                  ],
                  "type": "gt"
                },
                "operator": {
                  "type": "and"
                },
                "query": {
                  "datasourceId": 1,
                  "model": {
                    "expr": "rate(gm_dbmw_runtime_state_total_input_element_count{service_name=\"gaia-online\"}[1m])",
                    "intervalFactor": 2,
                    "legendFormat": "{{connection_name}}",
                    "metric": "gm_dbmw",
                    "refId": "A",
                    "step": 10
                  },
                  "params": [
                    "A",
                    "5m",
                    "now"
                  ]
                },
                "reducer": {
                  "params": [],
                  "type": "avg"
                },
                "type": "query"
              }
            ],
            "executionErrorState": "alerting",
            "frequency": "15m",
            "handler": 1,
            "name": "gaia-dbmw-taskrate",
            "noDataState": "no_data",
            "notifications": [
              {
                "id": 3
              },
              {
                "id": 2
              }
            ]
          },
          "aliasColors": {},
          "bars": false,
          "dashLength": 10,
          "dashes": false,
          "datasource": "${DS_PROMETHEUS}",
          "editable": true,
          "error": false,
          "fill": 0,
          "id": 2,
          "legend": {
            "avg": false,
            "current": false,
            "max": false,
            "min": false,
            "show": true,
            "total": false,
            "values": false
          },
          "lines": true,
          "linewidth": 1,
          "links": [],
          "nullPointMode": "connected",
          "percentage": false,
          "pointradius": 5,
          "points": false,
          "renderer": "flot",
          "seriesOverrides": [],
          "spaceLength": 10,
          "span": 12,
          "stack": false,
          "steppedLine": false,
          "targets": [
            {
              "expr": "rate(gm_dbmw_runtime_state_total_input_element_count{service_name=\"gaia-online\"}[1m])",
              "intervalFactor": 2,
              "legendFormat": "{{connection_name}}",
              "metric": "gm_dbmw",
              "refId": "A",
              "step": 10
            }
          ],
          "thresholds": [
            {
              "colorMode": "critical",
              "fill": true,
              "line": true,
              "op": "gt",
              "value": 10000
            }
          ],
          "timeFrom": null,
          "timeShift": null,
          "title": "gaia-dbmw-taskrate",
          "tooltip": {
            "msResolution": false,
            "shared": true,
            "sort": 0,
            "value_type": "individual"
          },
          "type": "graph",
          "xaxis": {
            "buckets": null,
            "mode": "time",
            "name": null,
            "show": true,
            "values": []
          },
          "yaxes": [
            {
              "format": "short",
              "label": null,
              "logBase": 1,
              "max": null,
              "min": null,
              "show": true
            },
            {
              "format": "short",
              "label": null,
              "logBase": 1,
              "max": null,
              "min": null,
              "show": true
            }
          ]
        }
      ],
      "repeat": null,
      "repeatIteration": null,
      "repeatRowId": null,
      "showTitle": false,
      "title": "Dashboard Row",
      "titleSize": "h6"
    },
    {
      "collapse": false,
      "height": 250,
      "panels": [
        {
          "alert": {
            "conditions": [
              {
                "evaluator": {
                  "params": [
                    3000
                  ],
                  "type": "gt"
                },
                "operator": {
                  "type": "and"
                },
                "query": {
                  "datasourceId": 1,
                  "model": {
                    "expr": "1000 * max(argus_export_service_realtime{service=\"backend\",type=\"avg\"}) by (service, ma_millis, type)",
                    "intervalFactor": 2,
                    "legendFormat": "{{service}}.{{ma_millis}}.{{type}}",
                    "metric": "",
                    "refId": "A",
                    "step": 10
                  },
                  "params": [
                    "A",
                    "5m",
                    "now"
                  ]
                },
                "reducer": {
                  "params": [],
                  "type": "max"
                },
                "type": "query"
              }
            ],
            "executionErrorState": "alerting",
            "frequency": "60s",
            "handler": 1,
            "name": "Backend请求时间平均值",
            "noDataState": "no_data",
            "notifications": [
              {
                "id": 3
              },
              {
                "id": 2
              }
            ]
          },
          "aliasColors": {},
          "bars": false,
          "dashLength": 10,
          "dashes": false,
          "datasource": "${DS_PROMETHEUS}",
          "editable": true,
          "error": false,
          "fill": 0,
          "id": 3,
          "legend": {
            "avg": false,
            "current": false,
            "max": false,
            "min": false,
            "show": true,
            "total": false,
            "values": false
          },
          "lines": true,
          "linewidth": 1,
          "links": [],
          "nullPointMode": "connected",
          "percentage": false,
          "pointradius": 5,
          "points": false,
          "renderer": "flot",
          "seriesOverrides": [],
          "spaceLength": 10,
          "span": 12,
          "stack": false,
          "steppedLine": false,
          "targets": [
            {
              "expr": "1000 * max(argus_export_service_realtime{service=\"backend\",type=\"avg\"}) by (service, ma_millis, type)",
              "intervalFactor": 2,
              "legendFormat": "{{service}}.{{ma_millis}}.{{type}}",
              "metric": "",
              "refId": "A",
              "step": 10
            }
          ],
          "thresholds": [
            {
              "colorMode": "critical",
              "fill": true,
              "line": true,
              "op": "gt",
              "value": 3000
            }
          ],
          "timeFrom": null,
          "timeShift": null,
          "title": "backend call time avg",
          "tooltip": {
            "msResolution": false,
            "shared": true,
            "sort": 0,
            "value_type": "individual"
          },
          "type": "graph",
          "xaxis": {
            "buckets": null,
            "mode": "time",
            "name": null,
            "show": true,
            "values": []
          },
          "yaxes": [
            {
              "format": "ms",
              "label": null,
              "logBase": 1,
              "max": null,
              "min": null,
              "show": true
            },
            {
              "format": "short",
              "label": null,
              "logBase": 1,
              "max": null,
              "min": null,
              "show": true
            }
          ]
        }
      ],
      "repeat": null,
      "repeatIteration": null,
      "repeatRowId": null,
      "showTitle": false,
      "title": "Dashboard Row",
      "titleSize": "h6"
    },
    {
      "collapse": false,
      "height": 323,
      "panels": [
        {
          "alert": {
            "conditions": [
              {
                "evaluator": {
                  "params": [
                    10000
                  ],
                  "type": "gt"
                },
                "operator": {
                  "type": "and"
                },
                "query": {
                  "datasourceId": 1,
                  "model": {
                    "expr": "jam_tasks_number{redis_broker=\"10.31.47.169:13010\", queue=\"celery\"}",
                    "hide": false,
                    "intervalFactor": 2,
                    "legendFormat": "{{redis_broker}}[{{queue}}]",
                    "metric": "",
                    "refId": "A",
                    "step": 10
                  },
                  "params": [
                    "A",
                    "5m",
                    "now"
                  ]
                },
                "reducer": {
                  "params": [],
                  "type": "avg"
                },
                "type": "query"
              },
              {
                "evaluator": {
                  "params": [
                    10000
                  ],
                  "type": "gt"
                },
                "operator": {
                  "type": "or"
                },
                "query": {
                  "datasourceId": 1,
                  "model": {
                    "expr": "jam_tasks_number{queue=~\".*.stat\"}",
                    "hide": false,
                    "intervalFactor": 2,
                    "legendFormat": "{{redis_broker}}[{{queue}}]",
                    "refId": "C",
                    "step": 10
                  },
                  "params": [
                    "C",
                    "5m",
                    "now"
                  ]
                },
                "reducer": {
                  "params": [],
                  "type": "avg"
                },
                "type": "query"
              },
              {
                "evaluator": {
                  "params": [
                    500
                  ],
                  "type": "gt"
                },
                "operator": {
                  "type": "or"
                },
                "query": {
                  "datasourceId": 1,
                  "model": {
                    "expr": "jam_tasks_number{redis_broker=\"10.31.47.169:13010\", queue!=\"celery\"}",
                    "hide": false,
                    "intervalFactor": 2,
                    "legendFormat": "{{redis_broker}}[{{queue}}]",
                    "refId": "B",
                    "step": 10
                  },
                  "params": [
                    "B",
                    "5m",
                    "now"
                  ]
                },
                "reducer": {
                  "params": [],
                  "type": "avg"
                },
                "type": "query"
              },
              {
                "evaluator": {
                  "params": [
                    500
                  ],
                  "type": "gt"
                },
                "operator": {
                  "type": "or"
                },
                "query": {
                  "datasourceId": 1,
                  "model": {
                    "expr": "jam_tasks_number{redis_broker!=\"10.31.47.169:13010\", queue!~\".*.stat\"}",
                    "intervalFactor": 2,
                    "legendFormat": "{{redis_broker}}[{{queue}}]",
                    "refId": "D",
                    "step": 10
                  },
                  "params": [
                    "D",
                    "5m",
                    "now"
                  ]
                },
                "reducer": {
                  "params": [],
                  "type": "avg"
                },
                "type": "query"
              }
            ],
            "executionErrorState": "alerting",
            "frequency": "60s",
            "handler": 1,
            "message": "gaia celery 队列长度超过1k",
            "name": "Celery队列长度监控",
            "noDataState": "no_data",
            "notifications": [
              {
                "id": 3
              },
              {
                "id": 2
              }
            ]
          },
          "aliasColors": {},
          "bars": false,
          "dashLength": 10,
          "dashes": false,
          "datasource": "${DS_PROMETHEUS}",
          "editable": true,
          "error": false,
          "fill": 0,
          "id": 4,
          "legend": {
            "alignAsTable": true,
            "avg": false,
            "current": true,
            "max": true,
            "min": false,
            "rightSide": true,
            "show": true,
            "sort": "max",
            "sortDesc": true,
            "total": false,
            "values": true
          },
          "lines": true,
          "linewidth": 1,
          "links": [],
          "nullPointMode": "connected",
          "percentage": false,
          "pointradius": 5,
          "points": false,
          "renderer": "flot",
          "seriesOverrides": [
            {
              "alias": "10.31.47.169:13010[celery]",
              "yaxis": 2
            },
            {
              "alias": "10.29.177.141:13008[doctor.stat]",
              "yaxis": 2
            },
            {
              "alias": "10.29.177.141:13008[user.stat]",
              "yaxis": 2
            }
          ],
          "spaceLength": 10,
          "span": 12,
          "stack": false,
          "steppedLine": false,
          "targets": [
            {
              "expr": "jam_tasks_number{redis_broker=\"10.31.47.169:13010\", queue=\"celery\"}",
              "format": "time_series",
              "hide": false,
              "intervalFactor": 2,
              "legendFormat": "{{redis_broker}}[{{queue}}]",
              "metric": "",
              "refId": "A",
              "step": 10
            },
            {
              "expr": "jam_tasks_number{queue=~\".*.stat\"}",
              "format": "time_series",
              "hide": false,
              "intervalFactor": 2,
              "legendFormat": "{{redis_broker}}[{{queue}}]",
              "refId": "C",
              "step": 10
            },
            {
              "expr": "jam_tasks_number{redis_broker=\"10.31.47.169:13010\", queue!=\"celery\"}",
              "format": "time_series",
              "hide": false,
              "intervalFactor": 2,
              "legendFormat": "{{redis_broker}}[{{queue}}]",
              "refId": "B",
              "step": 10
            },
            {
              "expr": "jam_tasks_number{redis_broker!=\"10.31.47.169:13010\", queue!~\".*.stat\"}",
              "format": "time_series",
              "hide": false,
              "intervalFactor": 2,
              "legendFormat": "{{redis_broker}}[{{queue}}]",
              "refId": "D",
              "step": 10
            }
          ],
          "thresholds": [
            {
              "colorMode": "critical",
              "fill": true,
              "line": true,
              "op": "gt",
              "value": 10000
            }
          ],
          "timeFrom": null,
          "timeShift": null,
          "title": "Gaia-celery队列长度监控",
          "tooltip": {
            "msResolution": false,
            "shared": true,
            "sort": 0,
            "value_type": "individual"
          },
          "transparent": true,
          "type": "graph",
          "xaxis": {
            "buckets": null,
            "mode": "time",
            "name": null,
            "show": true,
            "values": []
          },
          "yaxes": [
            {
              "format": "short",
              "label": null,
              "logBase": 1,
              "max": null,
              "min": null,
              "show": true
            },
            {
              "format": "short",
              "label": null,
              "logBase": 1,
              "max": null,
              "min": null,
              "show": true
            }
          ]
        }
      ],
      "repeat": null,
      "repeatIteration": null,
      "repeatRowId": null,
      "showTitle": false,
      "title": "Dashboard Row",
      "titleSize": "h6"
    },
    {
      "collapse": false,
      "height": 256,
      "panels": [
        {
          "alert": {
            "conditions": [
              {
                "evaluator": {
                  "params": [
                    10240
                  ],
                  "type": "gt"
                },
                "operator": {
                  "type": "and"
                },
                "query": {
                  "params": [
                    "A",
                    "1m",
                    "now"
                  ]
                },
                "reducer": {
                  "params": [],
                  "type": "last"
                },
                "type": "query"
              }
            ],
            "executionErrorState": "alerting",
            "frequency": "10s",
            "handler": 1,
            "message": "gaia-celery队列长度 超过 1 @古仕通",
            "name": "Gaia-Celery队列长度监控 alert",
            "noDataState": "no_data",
            "notifications": [
              {
                "id": 4
              },
              {
                "id": 3
              },
              {
                "id": 2
              }
            ]
          },
          "aliasColors": {},
          "bars": false,
          "dashLength": 10,
          "dashes": false,
          "datasource": "${DS_PROMETHEUS}",
          "editable": true,
          "error": false,
          "fill": 0,
          "id": 5,
          "legend": {
            "alignAsTable": true,
            "avg": false,
            "current": true,
            "max": true,
            "min": false,
            "rightSide": true,
            "show": false,
            "sort": "max",
            "sortDesc": true,
            "total": false,
            "values": true
          },
          "lines": true,
          "linewidth": 1,
          "links": [],
          "nullPointMode": "connected",
          "percentage": false,
          "pointradius": 5,
          "points": false,
          "renderer": "flot",
          "seriesOverrides": [
            {
              "alias": "10.31.47.169:13010[celery]",
              "yaxis": 2
            },
            {
              "alias": "10.29.177.141:13008[doctor.stat]",
              "yaxis": 2
            },
            {
              "alias": "10.29.177.141:13008[user.stat]",
              "yaxis": 2
            }
          ],
          "spaceLength": 10,
          "span": 3,
          "stack": false,
          "steppedLine": false,
          "targets": [
            {
              "expr": "jam_tasks_number{redis_broker=\"10.31.47.169:13010\", queue=\"gaia-dbmw\"}",
              "format": "time_series",
              "hide": false,
              "intervalFactor": 2,
              "legendFormat": "{{redis_broker}}[{{queue}}]",
              "metric": "",
              "refId": "A",
              "step": 10
            }
          ],
          "thresholds": [
            {
              "colorMode": "critical",
              "fill": true,
              "line": true,
              "op": "gt",
              "value": 10240
            }
          ],
          "timeFrom": null,
          "timeShift": null,
          "title": "Gaia-dbmw队列长度监控",
          "tooltip": {
            "msResolution": false,
            "shared": true,
            "sort": 0,
            "value_type": "individual"
          },
          "transparent": true,
          "type": "graph",
          "xaxis": {
            "buckets": null,
            "mode": "time",
            "name": null,
            "show": true,
            "values": []
          },
          "yaxes": [
            {
              "format": "short",
              "label": null,
              "logBase": 1,
              "max": null,
              "min": null,
              "show": true
            },
            {
              "format": "short",
              "label": null,
              "logBase": 1,
              "max": null,
              "min": null,
              "show": true
            }
          ]
        },
        {
          "alert": {
            "conditions": [
              {
                "evaluator": {
                  "params": [
                    10000
                  ],
                  "type": "gt"
                },
                "operator": {
                  "type": "and"
                },
                "query": {
                  "params": [
                    "A",
                    "5m",
                    "now"
                  ]
                },
                "reducer": {
                  "params": [],
                  "type": "avg"
                },
                "type": "query"
              }
            ],
            "executionErrorState": "alerting",
            "frequency": "60s",
            "handler": 1,
            "message": "gaia-celery队列长度超过 1w  @古仕通",
            "name": "Mimas-Celery队列长度监控 alert",
            "noDataState": "no_data",
            "notifications": [
              {
                "id": 4
              },
              {
                "id": 3
              },
              {
                "id": 2
              }
            ]
          },
          "aliasColors": {},
          "bars": false,
          "dashLength": 10,
          "dashes": false,
          "datasource": "${DS_PROMETHEUS}",
          "editable": true,
          "error": false,
          "fill": 0,
          "id": 6,
          "legend": {
            "alignAsTable": true,
            "avg": false,
            "current": true,
            "max": true,
            "min": false,
            "rightSide": true,
            "show": false,
            "sort": "max",
            "sortDesc": true,
            "total": false,
            "values": true
          },
          "lines": true,
          "linewidth": 1,
          "links": [],
          "nullPointMode": "connected",
          "percentage": false,
          "pointradius": 5,
          "points": false,
          "renderer": "flot",
          "seriesOverrides": [
            {
              "alias": "10.31.47.169:13010[celery]",
              "yaxis": 2
            },
            {
              "alias": "10.29.177.141:13008[doctor.stat]",
              "yaxis": 2
            },
            {
              "alias": "10.29.177.141:13008[user.stat]",
              "yaxis": 2
            }
          ],
          "spaceLength": 10,
          "span": 3,
          "stack": false,
          "steppedLine": false,
          "targets": [
            {
              "expr": "jam_tasks_number{redis_broker=\"10.29.177.141:13029\", queue=\"mimas-dbmw\"}",
              "format": "time_series",
              "hide": false,
              "intervalFactor": 2,
              "legendFormat": "{{redis_broker}}[{{queue}}]",
              "metric": "",
              "refId": "A",
              "step": 10
            }
          ],
          "thresholds": [
            {
              "colorMode": "critical",
              "fill": true,
              "line": true,
              "op": "gt",
              "value": 10000
            }
          ],
          "timeFrom": null,
          "timeShift": null,
          "title": "Mimas-dbmw队列长度监控",
          "tooltip": {
            "msResolution": false,
            "shared": true,
            "sort": 0,
            "value_type": "individual"
          },
          "transparent": true,
          "type": "graph",
          "xaxis": {
            "buckets": null,
            "mode": "time",
            "name": null,
            "show": true,
            "values": []
          },
          "yaxes": [
            {
              "format": "short",
              "label": null,
              "logBase": 1,
              "max": null,
              "min": null,
              "show": true
            },
            {
              "format": "short",
              "label": null,
              "logBase": 1,
              "max": null,
              "min": null,
              "show": true
            }
          ]
        },
        {
          "aliasColors": {},
          "bars": false,
          "dashLength": 10,
          "dashes": false,
          "datasource": "${DS_PROMETHEUS}",
          "editable": true,
          "error": false,
          "fill": 0,
          "id": 7,
          "legend": {
            "alignAsTable": true,
            "avg": false,
            "current": true,
            "max": true,
            "min": false,
            "rightSide": true,
            "show": false,
            "sort": "max",
            "sortDesc": true,
            "total": false,
            "values": true
          },
          "lines": true,
          "linewidth": 1,
          "links": [],
          "nullPointMode": "connected",
          "percentage": false,
          "pointradius": 5,
          "points": false,
          "renderer": "flot",
          "seriesOverrides": [
            {
              "alias": "10.31.47.169:13010[celery]",
              "yaxis": 2
            },
            {
              "alias": "10.29.177.141:13008[doctor.stat]",
              "yaxis": 2
            },
            {
              "alias": "10.29.177.141:13008[user.stat]",
              "yaxis": 2
            }
          ],
          "spaceLength": 10,
          "span": 3,
          "stack": false,
          "steppedLine": false,
          "targets": [
            {
              "expr": "jam_tasks_number{redis_broker=\"10.29.177.141:13029\", queue=\"celery\"}",
              "format": "time_series",
              "hide": false,
              "intervalFactor": 2,
              "legendFormat": "{{redis_broker}}[{{queue}}]",
              "metric": "",
              "refId": "A",
              "step": 10
            }
          ],
          "thresholds": [],
          "timeFrom": null,
          "timeShift": null,
          "title": "Mimas-Celery队列长度监控",
          "tooltip": {
            "msResolution": false,
            "shared": true,
            "sort": 0,
            "value_type": "individual"
          },
          "transparent": true,
          "type": "graph",
          "xaxis": {
            "buckets": null,
            "mode": "time",
            "name": null,
            "show": true,
            "values": []
          },
          "yaxes": [
            {
              "format": "short",
              "label": null,
              "logBase": 1,
              "max": null,
              "min": null,
              "show": true
            },
            {
              "format": "short",
              "label": null,
              "logBase": 1,
              "max": null,
              "min": null,
              "show": true
            }
          ]
        },
        {
          "alert": {
            "conditions": [
              {
                "evaluator": {
                  "params": [
                    20
                  ],
                  "type": "gt"
                },
                "operator": {
                  "type": "and"
                },
                "query": {
                  "params": [
                    "A",
                    "5m",
                    "now"
                  ]
                },
                "reducer": {
                  "params": [],
                  "type": "avg"
                },
                "type": "query"
              }
            ],
            "executionErrorState": "alerting",
            "frequency": "60s",
            "handler": 1,
            "message": "Doctor-notify队列长度 超过 20  @倪嘉华",
            "name": "Doctor-notify队列长度监控 alert",
            "noDataState": "no_data",
            "notifications": [
              {
                "id": 5
              },
              {
                "id": 3
              },
              {
                "id": 2
              }
            ]
          },
          "aliasColors": {},
          "bars": false,
          "dashLength": 10,
          "dashes": false,
          "datasource": "${DS_PROMETHEUS}",
          "editable": true,
          "error": false,
          "fill": 0,
          "id": 8,
          "legend": {
            "alignAsTable": true,
            "avg": false,
            "current": true,
            "max": true,
            "min": false,
            "rightSide": true,
            "show": false,
            "sort": "max",
            "sortDesc": true,
            "total": false,
            "values": true
          },
          "lines": true,
          "linewidth": 1,
          "links": [],
          "nullPointMode": "connected",
          "percentage": false,
          "pointradius": 5,
          "points": false,
          "renderer": "flot",
          "seriesOverrides": [
            {
              "alias": "10.31.47.169:13010[celery]",
              "yaxis": 2
            },
            {
              "alias": "10.29.177.141:13008[doctor.stat]",
              "yaxis": 2
            },
            {
              "alias": "10.29.177.141:13008[user.stat]",
              "yaxis": 2
            }
          ],
          "spaceLength": 10,
          "span": 3,
          "stack": false,
          "steppedLine": false,
          "targets": [
            {
              "expr": "jam_tasks_number{redis_broker=\"10.31.47.169:13010\", queue=\"doctor-notify\"}",
              "format": "time_series",
              "hide": false,
              "intervalFactor": 2,
              "legendFormat": "{{redis_broker}}[{{queue}}]",
              "metric": "",
              "refId": "A",
              "step": 10
            }
          ],
          "thresholds": [
            {
              "colorMode": "critical",
              "fill": true,
              "line": true,
              "op": "gt",
              "value": 20
            }
          ],
          "timeFrom": null,
          "timeShift": null,
          "title": "Doctor-notify队列长度监控",
          "tooltip": {
            "msResolution": false,
            "shared": true,
            "sort": 0,
            "value_type": "individual"
          },
          "transparent": true,
          "type": "graph",
          "xaxis": {
            "buckets": null,
            "mode": "time",
            "name": null,
            "show": true,
            "values": []
          },
          "yaxes": [
            {
              "format": "short",
              "label": null,
              "logBase": 1,
              "max": null,
              "min": null,
              "show": true
            },
            {
              "format": "short",
              "label": null,
              "logBase": 1,
              "max": null,
              "min": null,
              "show": true
            }
          ]
        },
        {
          "alert": {
            "conditions": [
              {
                "evaluator": {
                  "params": [
                    10000
                  ],
                  "type": "gt"
                },
                "operator": {
                  "type": "and"
                },
                "query": {
                  "params": [
                    "A",
                    "5m",
                    "now"
                  ]
                },
                "reducer": {
                  "params": [],
                  "type": "avg"
                },
                "type": "query"
              }
            ],
            "executionErrorState": "alerting",
            "frequency": "60s",
            "handler": 1,
            "message": "gaia-celery 队列长度超过 1w @古仕通",
            "name": "Gaia-dbmw队列长度监控 alert",
            "noDataState": "no_data",
            "notifications": [
              {
                "id": 4
              },
              {
                "id": 3
              },
              {
                "id": 2
              }
            ]
          },
          "aliasColors": {},
          "bars": false,
          "dashLength": 10,
          "dashes": false,
          "datasource": "${DS_PROMETHEUS}",
          "editable": true,
          "error": false,
          "fill": 0,
          "id": 9,
          "legend": {
            "alignAsTable": true,
            "avg": false,
            "current": true,
            "max": true,
            "min": false,
            "rightSide": true,
            "show": true,
            "sort": "max",
            "sortDesc": true,
            "total": false,
            "values": true
          },
          "lines": true,
          "linewidth": 1,
          "links": [],
          "nullPointMode": "connected",
          "percentage": false,
          "pointradius": 5,
          "points": false,
          "renderer": "flot",
          "seriesOverrides": [
            {
              "alias": "10.31.47.169:13010[celery]",
              "yaxis": 2
            },
            {
              "alias": "10.29.177.141:13008[doctor.stat]",
              "yaxis": 2
            },
            {
              "alias": "10.29.177.141:13008[user.stat]",
              "yaxis": 2
            }
          ],
          "spaceLength": 10,
          "span": 3,
          "stack": false,
          "steppedLine": false,
          "targets": [
            {
              "expr": "jam_tasks_number{redis_broker=\"10.31.47.169:13010\", queue=\"celery\"}",
              "format": "time_series",
              "hide": false,
              "intervalFactor": 2,
              "legendFormat": "{{redis_broker}}[{{queue}}]",
              "metric": "",
              "refId": "A",
              "step": 10
            }
          ],
          "thresholds": [
            {
              "colorMode": "critical",
              "fill": true,
              "line": true,
              "op": "gt",
              "value": 10000
            }
          ],
          "timeFrom": null,
          "timeShift": null,
          "title": "Gaia-dbmw队列长度监控",
          "tooltip": {
            "msResolution": false,
            "shared": true,
            "sort": 0,
            "value_type": "individual"
          },
          "transparent": true,
          "type": "graph",
          "xaxis": {
            "buckets": null,
            "mode": "time",
            "name": null,
            "show": true,
            "values": []
          },
          "yaxes": [
            {
              "format": "short",
              "label": null,
              "logBase": 1,
              "max": null,
              "min": null,
              "show": true
            },
            {
              "format": "short",
              "label": null,
              "logBase": 1,
              "max": null,
              "min": null,
              "show": true
            }
          ]
        }
      ],
      "repeat": null,
      "repeatIteration": null,
      "repeatRowId": null,
      "showTitle": false,
      "title": "Dashboard Row",
      "titleSize": "h6"
    }
  ],
  "schemaVersion": 14,
  "style": "dark",
  "tags": [],
  "templating": {
    "list": []
  },
  "time": {
    "from": "now-7d",
    "to": "now"
  },
  "timepicker": {
    "refresh_intervals": [
      "5s",
      "10s",
      "30s",
      "1m",
      "5m",
      "15m",
      "30m",
      "1h",
      "2h",
      "1d"
    ],
    "time_options": [
      "5m",
      "15m",
      "1h",
      "6h",
      "12h",
      "24h",
      "2d",
      "7d",
      "30d"
    ]
  },
  "timezone": "browser",
  "title": "alert manger",
  "version": 68
}